net.py
netstat_cl-0.1.3.dist-info/DESCRIPTION.rst
netstat_cl-0.1.3.dist-info/METADATA
netstat_cl-0.1.3.dist-info/RECORD
netstat_cl-0.1.3.dist-info/WHEEL
netstat_cl-0.1.3.dist-info/entry_points.txt
netstat_cl-0.1.3.dist-info/metadata.json
netstat_cl-0.1.3.dist-info/top_level.txt
