Metadata-Version: 2.0
Name: netstat-cl
Version: 0.1.3
Summary: Ubuntu Indicator to display net usage and speed on Unity taskbar.
Home-page: https://github.com/shubhodeep9/python-netstat
Author: Shubhodeep Mukherjee
Author-email: shubhodeep9@gmail.com
License: Apache License, Version 2.0
Keywords: Ubuntu,Internet speed
Platform: UNKNOWN
Classifier: Development Status :: 3 - Alpha
Classifier: Programming Language :: Python
Classifier: Environment :: Console
Classifier: License :: OSI Approved :: Apache Software License
Classifier: Operating System :: OS Independent
Classifier: Programming Language :: Python :: 2
Classifier: Programming Language :: Python :: 2.4
Classifier: Programming Language :: Python :: 2.5
Classifier: Programming Language :: Python :: 2.6
Classifier: Programming Language :: Python :: 2.7
Classifier: Programming Language :: Python :: 3
Classifier: Programming Language :: Python :: 3.1
Classifier: Programming Language :: Python :: 3.2
Classifier: Programming Language :: Python :: 3.3
Classifier: Programming Language :: Python :: 3.4
Requires-Dist: netifaces (==0.10.4)
Requires-Dist: psutil (==4.3.0)
